setup.cfg
setup.py
cartographer/__init__.py
cartographer.egg-info/PKG-INFO
cartographer.egg-info/SOURCES.txt
cartographer.egg-info/dependency_links.txt
cartographer.egg-info/requires.txt
cartographer.egg-info/top_level.txt
cartographer.egg-info/zip-safe
cartographer/exceptions/__init__.py
cartographer/exceptions/request_exceptions.py
cartographer/field_types/__init__.py
cartographer/field_types/array_relationship.py
cartographer/field_types/bool_attribute.py
cartographer/field_types/date_attribute.py
cartographer/field_types/int_attribute.py
cartographer/field_types/json_attribute.py
cartographer/field_types/schema_attribute.py
cartographer/field_types/schema_relationship.py
cartographer/field_types/string_attribute.py
cartographer/parsers/__init__.py
cartographer/parsers/jsonapi_parser.py
cartographer/parsers/schema_parser.py
cartographer/permissions/__init__.py
cartographer/permissions/base_mask.py
cartographer/requests/__init__.py
cartographer/requests/jsonapi_flask_request_mixin.py
cartographer/requests/jsonapi_request_interface.py
cartographer/requests/session_interface.py
cartographer/resources/__init__.py
cartographer/resources/api_resource.py
cartographer/resources/resource_registry.py
cartographer/schemas/__init__.py
cartographer/schemas/schema.py
cartographer/serializers/__init__.py
cartographer/serializers/jsonapi_collection_serializer.py
cartographer/serializers/jsonapi_null_serializer.py
cartographer/serializers/jsonapi_serializer.py
cartographer/serializers/schema_serializer.py
cartographer/utils/__init__.py
cartographer/utils/collections.py
cartographer/utils/config.py
cartographer/utils/datetime.py
cartographer/utils/version.py
test/test_jsonapi_flask_request_mixin.py
test/test_jsonapi_serializer.py