Metadata-Version: 1.1
Name: cartographer
Version: 0.2.0-alpha3
Summary: Python library for using JSON API, especially with Flask.
Home-page: http://github.com/Patreon/cartographer
Author: Patreon
Author-email: david@patreon.com
License: Apache 2.0
Platform: UNKNOWN
Classifier: Development Status :: 2 - Pre-Alpha
Classifier: Environment :: Web Environment
Classifier: Framework :: Flask
Classifier: Intended Audience :: Developers
Classifier: License :: OSI Approved :: Apache Software License
Classifier: Operating System :: OS Independent
Classifier: Programming Language :: Python
Classifier: Programming Language :: Python :: 3
Classifier: Programming Language :: Python :: 3.4
Classifier: Programming Language :: Python :: 3.5
Classifier: Topic :: Internet :: WWW/HTTP
Classifier: Topic :: Internet :: WWW/HTTP :: Dynamic Content
Classifier: Topic :: Software Development :: Libraries :: Python Modules
